{
	"name": "byg:orange_spruce",
    "mod": "byg",
    "sapling": {
        "name": "byg:orangesprucesapling",
        "data": 0
    },
    "growTimeMultiplier": 0.9,
    "drops": [
        {
            "name": "minecraft:stick",
            "data": 0,
            "type": "STICK"
        },
        {
            "name": "minecraft:log",
            "data": 1,
            "type": "WOOD"
        },
        {
            "name": "byg:orangesprucesapling",
            "data": 0,
            "type": "SAPLING"
        },
        {
            "name": "byg:spruceleavesorange",
            "data": 0,
            "type": "LEAVES"
        }
    ]
}