{
  "type": "abyssalcraft:dreadsapling",
  "version": 2,
  "ref": {
    "a": {
      "name": "abyssalcraft:dreadleaves",
      "meta": 8
    },
    "b": {
      "name": "abyssalcraft:dreadlog",
      "meta": 12
    },
    "c": {
      "name": "abyssalcraft:dreadlog",
      "meta": 0
    }
  },
  "shape": [
    [
      "       a   ",
      "    a  b   ",
      "    b      ",
      "           ",
      "           ",
      "           ",
      "           ",
      "           ",
      "           ",
      "           ",
      "           ",
      "           "
    ],
    [
      "           ",
      "    a a    ",
      "    b b    ",
      "           ",
      "           ",
      "           ",
      "           ",
      "           ",
      "           ",
      "           ",
      "           ",
      "           "
    ],
    [
      "a          ",
      "b     a    ",
      "    a b    ",
      "    b      ",
      "           ",
      "           ",
      "           ",
      "           ",
      "           ",
      "           ",
      "           ",
      "           "
    ],
    [
      " a         ",
      " ba      aa",
      "  b  aa  bb",
      "     bb    ",
      "           ",
      "           ",
      "           ",
      "           ",
      "           ",
      "           ",
      "           ",
      "           "
    ],
    [
      "           ",
      "   a       ",
      "   baa aa  ",
      "    bb bb  ",
      "     b     ",
      "           ",
      "           ",
      "           ",
      "           ",
      "           ",
      "           ",
      "     b     "
    ],
    [
      "a        a ",
      "baa  a aab ",
      " bbaacabb  ",
      "   bbbb    ",
      "     bb    ",
      "     c     ",
      "     c     ",
      "     c     ",
      "     c     ",
      "     cb    ",
      "     cc    ",
      "    bcc    "
    ],
    [
      "          a",
      "          b",
      "     a     ",
      "    aba    ",
      "    b b    ",
      "           ",
      "           ",
      "           ",
      "           ",
      "           ",
      "     b     ",
      "     c     "
    ],
    [
      "           ",
      "     a     ",
      "    aba    ",
      "    b b    ",
      "           ",
      "           ",
      "           ",
      "           ",
      "           ",
      "           ",
      "           ",
      "           "
    ],
    [
      "           ",
      "  a  a  a  ",
      "  ba b ab  ",
      "   b   b   ",
      "           ",
      "           ",
      "           ",
      "           ",
      "           ",
      "           ",
      "           ",
      "           "
    ],
    [
      "     a     ",
      "  a  b  a  ",
      "  b     b  ",
      "           ",
      "           ",
      "           ",
      "           ",
      "           ",
      "           ",
      "           ",
      "           ",
      "           "
    ],
    [
      "     a     ",
      "     b     ",
      "           ",
      "           ",
      "           ",
      "           ",
      "           ",
      "           ",
      "           ",
      "           ",
      "           ",
      "           "
    ]
  ]
}
