{
  "type": "forestry:cocobolo",
  "version": 2,
  "ref": {
    "a": {
      "name": "forestry:logs.6",
      "meta": 3
    },
    "b": {
      "name": "forestry:leaves.decorative.1",
      "meta": 10
    }
  },
  "shape": [
    [
      "         ",
      "         ",
      "         ",
      "         ",
      "         ",
      "         ",
      "         ",
      "         ",
      "     b   ",
      "         ",
      "         ",
      "         ",
      "         ",
      "         ",
      "         "
    ],
    [
      "         ",
      "         ",
      "    b    ",
      "         ",
      "         ",
      "         ",
      "         ",
      "         ",
      "   bbbbb ",
      "         ",
      "         ",
      "         ",
      "         ",
      "         ",
      "         "
    ],
    [
      "         ",
      "    b    ",
      "  bbbbb  ",
      "         ",
      "   b     ",
      "     b   ",
      "   b     ",
      "     b   ",
      "   bbbbb ",
      "     b   ",
      "         ",
      "         ",
      "         ",
      "         ",
      "         "
    ],
    [
      "         ",
      "   bbb   ",
      "  bbbbb  ",
      "    b    ",
      " bbbbb   ",
      "    bbb  ",
      " bbbbb   ",
      "    bbb  ",
      "  bbbbbbb",
      "    bbb  ",
      "         ",
      "         ",
      "         ",
      "         ",
      "         "
    ],
    [
      "    b    ",
      "  bbabb  ",
      " bbbabbb ",
      "   bab   ",
      " bbbab   ",
      "    ab   ",
      " bbbab   ",
      "    ab   ",
      "   babbb ",
      "    ab   ",
      "    a    ",
      "    a    ",
      "    a    ",
      "    a    ",
      "    a    "
    ],
    [
      "         ",
      "   bbb   ",
      "  bbbbb  ",
      "    b    ",
      "bbbbbbb  ",
      "         ",
      "bbbbbbb  ",
      "         ",
      "   bbbbb ",
      "         ",
      "         ",
      "         ",
      "         ",
      "         ",
      "         "
    ],
    [
      "         ",
      "    b    ",
      "  bbbbb  ",
      "         ",
      " bbbbb   ",
      "         ",
      " bbbbb   ",
      "         ",
      "     b   ",
      "         ",
      "         ",
      "         ",
      "         ",
      "         ",
      "         "
    ],
    [
      "         ",
      "         ",
      "    b    ",
      "         ",
      " bbbbb   ",
      "         ",
      " bbbbb   ",
      "         ",
      "         ",
      "         ",
      "         ",
      "         ",
      "         ",
      "         ",
      "         "
    ],
    [
      "         ",
      "         ",
      "         ",
      "         ",
      "   b     ",
      "         ",
      "   b     ",
      "         ",
      "         ",
      "         ",
      "         ",
      "         ",
      "         ",
      "         ",
      "         "
    ]
  ]
}
